api/application.py
nlp_ood-0.1.1.dist-info/METADATA
nlp_ood-0.1.1.dist-info/WHEEL
nlp_ood-0.1.1.dist-info/top_level.txt
nlp_ood-0.1.1.dist-info/RECORD
