Metadata-Version: 2.1
Name: nlp-ood
Version: 0.1.1
Summary: domain classification
Author: Developer
License: MIT
Classifier: Intended Audience :: Developers
Classifier: Intended Audience :: Science/Research
Classifier: Operating System :: OS Independent
Classifier: Programming Language :: Python :: 3
Classifier: Topic :: Scientific/Engineering :: Artificial Intelligence
Requires-Python: >=3.7
Requires-Dist: uvicorn
Requires-Dist: python-dotenv
Requires-Dist: fastapi
Requires-Dist: loguru
Requires-Dist: numpy
Requires-Dist: torch
Requires-Dist: transformers
Requires-Dist: vncorenlp
Requires-Dist: pymongo
